meteogram/__init__.py
meteogram/api.py
meteogram/commandline_script.py
meteogram/constants.py
meteogram/get_weather_data.py
meteogram/make_meteogram.py
meteogram/schemas.py
meteogram/weather_symbols/LICENSE
meteogram/weather_symbols/__init__.py
meteogram/weather_symbols/pdf/clearsky_day.pdf
meteogram/weather_symbols/pdf/clearsky_night.pdf
meteogram/weather_symbols/pdf/clearsky_polartwilight.pdf
meteogram/weather_symbols/pdf/cloudy.pdf
meteogram/weather_symbols/pdf/fair_day.pdf
meteogram/weather_symbols/pdf/fair_night.pdf
meteogram/weather_symbols/pdf/fair_polartwilight.pdf
meteogram/weather_symbols/pdf/fog.pdf
meteogram/weather_symbols/pdf/heavyrain.pdf
meteogram/weather_symbols/pdf/heavyrainandthunder.pdf
meteogram/weather_symbols/pdf/heavyrainshowers_day.pdf
meteogram/weather_symbols/pdf/heavyrainshowers_night.pdf
meteogram/weather_symbols/pdf/heavyrainshowers_polartwilight.pdf
meteogram/weather_symbols/pdf/heavyrainshowersandthunder_day.pdf
meteogram/weather_symbols/pdf/heavyrainshowersandthunder_night.pdf
meteogram/weather_symbols/pdf/heavyrainshowersandthunder_polartwilight.pdf
meteogram/weather_symbols/pdf/heavysleet.pdf
meteogram/weather_symbols/pdf/heavysleetandthunder.pdf
meteogram/weather_symbols/pdf/heavysleetshowers_day.pdf
meteogram/weather_symbols/pdf/heavysleetshowers_night.pdf
meteogram/weather_symbols/pdf/heavysleetshowers_polartwilight.pdf
meteogram/weather_symbols/pdf/heavysleetshowersandthunder_day.pdf
meteogram/weather_symbols/pdf/heavysleetshowersandthunder_night.pdf
meteogram/weather_symbols/pdf/heavysleetshowersandthunder_polartwilight.pdf
meteogram/weather_symbols/pdf/heavysnow.pdf
meteogram/weather_symbols/pdf/heavysnowandthunder.pdf
meteogram/weather_symbols/pdf/heavysnowshowers_day.pdf
meteogram/weather_symbols/pdf/heavysnowshowers_night.pdf
meteogram/weather_symbols/pdf/heavysnowshowers_polartwilight.pdf
meteogram/weather_symbols/pdf/heavysnowshowersandthunder_day.pdf
meteogram/weather_symbols/pdf/heavysnowshowersandthunder_night.pdf
meteogram-0.1.2.dist-info/METADATA
meteogram-0.1.2.dist-info/WHEEL
meteogram-0.1.2.dist-info/top_level.txt
meteogram-0.1.2.dist-info/RECORD
