Metadata-Version: 2.4
Name: meteogram
Version: 0.1.2
Summary: Create meteogram based on data from met.no
Author-email: Martin Høy <martin@hoy.priv.no>
Requires-Python: >=3.10
Requires-Dist: loguru>=0.7.3
Requires-Dist: pandas>=2.2.3
Requires-Dist: pydantic>=2.10.6
Requires-Dist: pydantic-settings>=2.8.1
Requires-Dist: python-dotenv>=1.0.1
Requires-Dist: requests>=2.32.3
Requires-Dist: requests-cache>=1.2.1
Requires-Dist: scipy>=1.15.2
Requires-Dist: matplotlib>=3.10.1
Requires-Dist: fastapi>=0.115.10
Requires-Dist: uvicorn>=0.34.0
